video_duration_tool/__init__.py
video_duration_tool/duration.py
vidtally-0.1.0.dist-info/licenses/LICENSE
vidtally-0.1.0.dist-info/METADATA
vidtally-0.1.0.dist-info/WHEEL
vidtally-0.1.0.dist-info/entry_points.txt
vidtally-0.1.0.dist-info/top_level.txt
vidtally-0.1.0.dist-info/RECORD
