Metadata-Version: 2.4
Name: vidtally
Version: 0.1.0
Summary: VidTally: A beautiful CLI tool to tally durations of MP4 files in a folder
Author: Abdul Rehman Yousaf
Author-email: abdul@9to5ml.com
License: MIT
Classifier: Programming Language :: Python :: 3
Classifier: License :: OSI Approved :: MIT License
Classifier: Operating System :: OS Independent
Requires-Python: >=3.6
License-File: LICENSE
Requires-Dist: rich
Requires-Dist: pyfiglet
Requires-Dist: typer
Dynamic: author
Dynamic: author-email
Dynamic: classifier
Dynamic: description
Dynamic: description-content-type
Dynamic: license
Dynamic: license-file
Dynamic: requires-dist
Dynamic: requires-python
Dynamic: summary
